{
	"title": "4DV4 Drone with 1080P Camera for Adults,HD FPV Live Video RC Quadcopter Helicopter for Beginners Kids Toys Gifts,2 Batteries and Carrying Case,Altitude Hold,Waypoints,3D Flip,Headless Mode,Black",
	"asin": "B096KR7D6N",
	"itemUrl": "https://www.amazon.com/Foldable-Quadcopter-Altitude-Waypoints-Batteries/dp/B096KR7D6N/ref=sr_1_39?keywords=drone&qid=1674944744&sr=8-39",
	"keyword": "drone",
	"description": "",
	"sellerName": "4DRc",
	"offer": "$99.99",
	"aodImage": "https://m.media-amazon.com/images/I/41uk2R1FphL.jpg"
}