{
	"id": "cqxi0w3k0pHgOBg",
	"json": "{\"id\":\"cqxi0w3k0pHgOBg\",\"url\":\"https://apify.com/mshopik/timbuk2-scraper\",\"loadedUrl\":\"https://apify.com/mshopik/timbuk2-scraper\",\"uniqueKey\":\"https://apify.com/mshopik/timbuk2-scraper\",\"method\":\"GET\",\"noRetry\":false,\"retryCount\":0,\"errorMessages\":[],\"headers\":{},\"userData\":{\"label\":\"DETAIL\",\"__crawlee\":{\"state\":4}},\"handledAt\":\"2023-01-25T16:49:16.852Z\"}",
	"method": "GET",
	"orderNo": null,
	"retryCount": 0,
	"uniqueKey": "https://apify.com/mshopik/timbuk2-scraper",
	"url": "https://apify.com/mshopik/timbuk2-scraper"
}