{
	"id": "vVsyGsog6i5j1AM",
	"json": "{\"id\":\"vVsyGsog6i5j1AM\",\"url\":\"https://apify.com/lukas.novotny/ubuntu-images-scraper\",\"loadedUrl\":\"https://apify.com/lukas.novotny/ubuntu-images-scraper\",\"uniqueKey\":\"https://apify.com/lukas.novotny/ubuntu-images-scraper\",\"method\":\"GET\",\"noRetry\":false,\"retryCount\":0,\"errorMessages\":[],\"headers\":{},\"userData\":{\"label\":\"DETAIL\",\"__crawlee\":{\"state\":4}},\"handledAt\":\"2023-01-25T16:55:57.449Z\"}",
	"method": "GET",
	"orderNo": null,
	"retryCount": 0,
	"uniqueKey": "https://apify.com/lukas.novotny/ubuntu-images-scraper",
	"url": "https://apify.com/lukas.novotny/ubuntu-images-scraper"
}