{
	"id": "d8DRXw7TJXJwsva",
	"json": "{\"id\":\"d8DRXw7TJXJwsva\",\"url\":\"https://www.compradiccion.com\",\"loadedUrl\":\"https://www.compradiccion.com/\",\"uniqueKey\":\"https://www.compradiccion.com\",\"method\":\"GET\",\"noRetry\":false,\"retryCount\":0,\"errorMessages\":[],\"headers\":{},\"userData\":{\"label\":\"DOMAIN RESULT\",\"__crawlee\":{\"state\":4}},\"handledAt\":\"2023-01-27T16:33:33.835Z\"}",
	"method": "GET",
	"orderNo": null,
	"retryCount": 0,
	"uniqueKey": "https://www.compradiccion.com",
	"url": "https://www.compradiccion.com"
}