{
	"id": "YReH9zTJ8tOdjVj",
	"json": "{\"id\":\"YReH9zTJ8tOdjVj\",\"url\":\"https://www.peixotocortinas.com.br\",\"loadedUrl\":\"https://www.peixotocortinas.com.br/\",\"uniqueKey\":\"https://www.peixotocortinas.com.br\",\"method\":\"GET\",\"noRetry\":false,\"retryCount\":0,\"errorMessages\":[],\"headers\":{},\"userData\":{\"label\":\"DOMAIN RESULT\",\"__crawlee\":{\"state\":4}},\"handledAt\":\"2023-01-27T16:32:40.724Z\"}",
	"method": "GET",
	"orderNo": null,
	"retryCount": 0,
	"uniqueKey": "https://www.peixotocortinas.com.br",
	"url": "https://www.peixotocortinas.com.br"
}